APACHE.txt
README.txt
setup.cfg
setup.py
collective/__init__.py
collective.pfg.sslfield.egg-info/PKG-INFO
collective.pfg.sslfield.egg-info/SOURCES.txt
collective.pfg.sslfield.egg-info/dependency_links.txt
collective.pfg.sslfield.egg-info/entry_points.txt
collective.pfg.sslfield.egg-info/namespace_packages.txt
collective.pfg.sslfield.egg-info/not-zip-safe
collective.pfg.sslfield.egg-info/requires.txt
collective.pfg.sslfield.egg-info/top_level.txt
collective/pfg/__init__.py
collective/pfg/sslfield/__init__.py
collective/pfg/sslfield/config.py
collective/pfg/sslfield/configure.zcml
collective/pfg/sslfield/dummy.pt
collective/pfg/sslfield/rebuild_i18n.sh
collective/pfg/sslfield/tests.py
collective/pfg/sslfield/version.txt
collective/pfg/sslfield/Extensions/Install.py
collective/pfg/sslfield/Extensions/__init__.py
collective/pfg/sslfield/content/__init__.py
collective/pfg/sslfield/content/sslfield.py
collective/pfg/sslfield/locales/collective.pfg.sslfield-manual.pot
collective/pfg/sslfield/locales/collective.pfg.sslfield.pot
collective/pfg/sslfield/locales/es/LC_MESSAGES/collective.pfg.sslfield.mo
collective/pfg/sslfield/locales/es/LC_MESSAGES/collective.pfg.sslfield.po
collective/pfg/sslfield/locales/eu/LC_MESSAGES/collective.pfg.sslfield.mo
collective/pfg/sslfield/locales/eu/LC_MESSAGES/collective.pfg.sslfield.po
collective/pfg/sslfield/profiles/default/propertiestool.xml
collective/pfg/sslfield/profiles/default/types.xml
collective/pfg/sslfield/profiles/default/types/FormFolder.xml
collective/pfg/sslfield/profiles/default/types/FormSSLStringField.xml
collective/pfg/sslfield/skins/pfgssl_templates/SSLStringField.gif
collective/pfg/sslfield/skins/pfgssl_templates/ssl_string_widget.pt
docs/HISTORY.txt
docs/INSTALL.txt
docs/LICENSE.GPL
docs/LICENSE.txt