Metadata-Version: 1.0
Name: collective.pfg.sslfield
Version: 0.4
Summary: New field for PloneFormGen to extract SSL data from the request
Home-page: http://svn.plone.org/svn/collective/collective.pfg.sslfield
Author: Mikel Larreategi
Author-email: mlarreategi@codesyntax.com
License: GPL
Keywords: plone forms ssl formgeneration
Platform: UNKNOWN
Classifier: Framework :: Plone
Classifier: Programming Language :: Python
Classifier: Topic :: Software Development :: Libraries :: Python Modules
